README.md
setup.py
tap_purecloud/__init__.py
tap_purecloud/schemas.py
tap_purecloud/websocket_helper.py
tap_purecloud.egg-info/PKG-INFO
tap_purecloud.egg-info/SOURCES.txt
tap_purecloud.egg-info/dependency_links.txt
tap_purecloud.egg-info/entry_points.txt
tap_purecloud.egg-info/requires.txt
tap_purecloud.egg-info/top_level.txt